Metadata-Version: 2.4
Name: adafruit-circuitpython-ssd1325
Version: 2.0.2
Summary: DisplayIO driver for grayscale OLEDs drive by SSD1325
Author-email: Adafruit Industries <circuitpython@adafruit.com>
License: MIT
Project-URL: Homepage, https://github.com/adafruit/Adafruit_CircuitPython_SSD1325
Keywords: adafruit,blinka,circuitpython,micropython,ssd1325,oled,grayscale,displayio
Classifier: Intended Audience :: Developers
Classifier: Topic :: Software Development :: Libraries
Classifier: Topic :: Software Development :: Embedded Systems
Classifier: Topic :: System :: Hardware
Classifier: License :: OSI Approved :: MIT License
Classifier: Programming Language :: Python :: 3
License-File: LICENSE
Requires-Dist: Adafruit-Blinka
Provides-Extra: optional
Dynamic: license-file
